namespacedkubespawner/__init__.py
namespacedkubespawner/reflector.py
namespacedkubespawner/spawner.py
namespacedkubespawner-0.0.21.dist-info/LICENSE
namespacedkubespawner-0.0.21.dist-info/METADATA
namespacedkubespawner-0.0.21.dist-info/WHEEL
namespacedkubespawner-0.0.21.dist-info/top_level.txt
namespacedkubespawner-0.0.21.dist-info/RECORD
