Metadata-Version: 2.1
Name: namespacedkubespawner
Version: 0.0.21
Summary: Namespaced Spawner for Kubernetes
Home-page: http://github.com/lsst-sqre/namespacedkubespawner
Author: Adam Thornton
Author-email: athornton@lsst.org
License: MIT
Project-URL: Source, https://github.com/lsst-sqre/namespacedkubespawner
Project-URL: Tracker, https://github.com/lsst-sqre/namespacedkubespawner/issues
Platform: UNKNOWN
Requires-Python: >=3.5
Requires-Dist: jupyterhub-kubespawner (>=0.10.1)
